AUTHORS.rst
CONTRIBUTING.rst
HISTORY.rst
LICENSE
MANIFEST.in
README.rst
setup.cfg
setup.py
ec2yaml/__init__.py
ec2yaml/actions.py
ec2yaml/cli.py
ec2yaml/config.py
ec2yaml/elastic_ip.py
ec2yaml/errors.py
ec2yaml/instances.py
ec2yaml/security_groups.py
ec2yaml/utils.py
ec2yaml/volumes.py
ec2yaml.egg-info/PKG-INFO
ec2yaml.egg-info/SOURCES.txt
ec2yaml.egg-info/dependency_links.txt
ec2yaml.egg-info/entry_points.txt
ec2yaml.egg-info/not-zip-safe
ec2yaml.egg-info/requires.txt
ec2yaml.egg-info/top_level.txt
requirements/default.txt
requirements/docs.txt
requirements/testing.txt
tests/__init__.py
tests/test_config.py
tests/test_create_instance.py
tests/test_elastic_ip.py
tests/test_security_groups.py
tests/test_utils.py