Metadata-Version: 1.0
Name: ec2yaml
Version: 0.0.2
Summary: Materialize a YAML configuration into AWS EC2
Home-page: UNKNOWN
Author: Adam Venturella <aventurella@gmail.com>, Dino Petrone <dinopetrone@gmail.com>
Author-email: aventurella@gmail.com
License: BSD
Platform: UNKNOWN
Classifier: Development Status :: 2 - Pre-Alpha
Classifier: Intended Audience :: Developers
Classifier: License :: OSI Approved :: BSD License
Classifier: Natural Language :: English
Classifier: Programming Language :: Python :: 2
Classifier: Programming Language :: Python :: 2.6
Classifier: Programming Language :: Python :: 2.7
Classifier: Programming Language :: Python :: 3
Classifier: Programming Language :: Python :: 3.3
